<configs>
<!-- maxcount="1" 这个是倍数 -->
<!-- respawndelay="1" 这个应该是刷新延迟 -->
<!-- time="Day"  Day是白天生成，Night是晚上生成 -->
<!-- 森林僵尸，火烧地僵尸，沙漠僵尸，废墟僵尸，雪地僵尸，雪地僵尸，这些都有末途MOD的怪物生成-->

	<!-- Addition -->
	<append xpath="/spawning/biome[@name='pine_forest']">
		<spawn maxcount="2" respawndelay="1" time="Day" entitygroup="ZombiesAll" />
		<spawn maxcount="1" respawndelay="2.5" time="Day" entitygroup="森林僵尸" />
        <spawn maxcount="2" respawndelay="1.5" time="Night" entitygroup="森林僵尸" />
	</append>
	


	<!-- Addition -->
	<append xpath="/spawning/biome[@name='burnt_forest']">
		<spawn maxcount="2" respawndelay="1" time="Day" entitygroup="ZombiesAll" />
		<spawn maxcount="2" respawndelay="1" time="Any" entitygroup="火烧地僵尸" />
	</append>




	
	<!-- Addition -->
	<append xpath="/spawning/biome[@name='desert']">
		<spawn maxcount="2" respawndelay="1" time="Day" entitygroup="ZombiesAll" />
		<spawn maxcount="2" respawndelay="1" time="Any" entitygroup="沙漠僵尸" />

	</append>



	

	<!-- Addition -->
	<append xpath="/spawning/biome[@name='wasteland']">
		<spawn maxcount="2" respawndelay="1" time="Day" entitygroup="ZombiesAll" />
		<spawn maxcount="2" respawndelay="1" time="Any" entitygroup="废墟僵尸" />


	</append>


	<!-- Addition -->
	<append xpath="/spawning/biome[@name='snow']">
		<spawn maxcount="1" respawndelay="1" time="Day" entitygroup="ZombiesAll" />
		<spawn maxcount="2" respawndelay="1" time="Day" entitygroup="雪地僵尸" />



	</append>
	
</configs>